gPhotosAlbum_JPEGcompression/__init__.py
gPhotosAlbum_JPEGcompression/main.py
gPhotosAlbum_JPEGcompression/device_chromedriver_autoinstaller/__init__.py
gPhotosAlbum_JPEGcompression/device_chromedriver_autoinstaller/utils.py
gphotosalbum_jpegcompression-2.2.2.dist-info/METADATA
gphotosalbum_jpegcompression-2.2.2.dist-info/WHEEL
gphotosalbum_jpegcompression-2.2.2.dist-info/top_level.txt
gphotosalbum_jpegcompression-2.2.2.dist-info/RECORD
