Metadata-Version: 2.4
Name: gPhotosAlbum_JPEGcompression
Version: 2.2.2
Summary: Takes Google Photos Album (visible to anyone with url) and produces a zip file with compressed JPEGS.
Author: Abhishek Venkatachalam
Author-email: abhishek.venkatachalam06@gmail.com
Classifier: Programming Language :: Python :: 3
Classifier: License :: OSI Approved :: MIT License
Classifier: Operating System :: OS Independent
Requires-Python: >=3.8
Requires-Dist: pillow
Requires-Dist: tqdm
Requires-Dist: requests
Requires-Dist: selenium
Requires-Dist: psutil
Dynamic: author
Dynamic: author-email
Dynamic: classifier
Dynamic: description
Dynamic: description-content-type
Dynamic: requires-dist
Dynamic: requires-python
Dynamic: summary
